README.rst
manual_requirements.txt
requirements.txt
setup.py
open_dash_app/__init__.py
open_dash_app.egg-info/PKG-INFO
open_dash_app.egg-info/SOURCES.txt
open_dash_app.egg-info/dependency_links.txt
open_dash_app.egg-info/requires.txt
open_dash_app.egg-info/top_level.txt